pipelit/__init__.py
pipelit/_about.py
pipelit-0.0.1.dist-info/LICENSE
pipelit-0.0.1.dist-info/METADATA
pipelit-0.0.1.dist-info/WHEEL
pipelit-0.0.1.dist-info/top_level.txt
pipelit-0.0.1.dist-info/RECORD
